newrelic_lambda/__init__.py
newrelic_lambda/agent_protocol.py
newrelic_lambda/cloudwatch_logging.py
newrelic_lambda/event-sources.json
newrelic_lambda/lambda_handler.py
newrelic_lambda-0.1.9.dist-info/METADATA
newrelic_lambda-0.1.9.dist-info/WHEEL
newrelic_lambda-0.1.9.dist-info/top_level.txt
newrelic_lambda-0.1.9.dist-info/RECORD
